Metadata-Version: 2.1
Name: django-bay-polls
Version: 0.1
Summary: Django app to be used in conducting Web-based polls.
Home-page: https://github.com/stevemats/django-bay-polls
Author: Stevemats
Author-email: contact@stevemats.net
License: BSD License
Platform: UNKNOWN
Classifier: Environment :: Web Environment
Classifier: Framework :: Django
Classifier: Intended Audience :: Developers
Classifier: License :: OSI Approved :: BSD License
Classifier: Operating System :: OS Independent
Classifier: Programming Language :: Python
Classifier: Programming Language :: Python :: 3.5
Classifier: Programming Language :: Python :: 3.6
